odoo/addons/upgrade_analysis/README.rst
odoo/addons/upgrade_analysis/__init__.py
odoo/addons/upgrade_analysis/__manifest__.py
odoo/addons/upgrade_analysis/blacklist.py
odoo/addons/upgrade_analysis/compare.py
odoo/addons/upgrade_analysis/upgrade_log.py
odoo/addons/upgrade_analysis/i18n/ca.po
odoo/addons/upgrade_analysis/i18n/fr.po
odoo/addons/upgrade_analysis/i18n/upgrade_analysis.pot
odoo/addons/upgrade_analysis/migrations/14.0.1.0.0/pre-migrate.py
odoo/addons/upgrade_analysis/models/__init__.py
odoo/addons/upgrade_analysis/models/ir_module_module.py
odoo/addons/upgrade_analysis/models/upgrade_analysis.py
odoo/addons/upgrade_analysis/models/upgrade_attribute.py
odoo/addons/upgrade_analysis/models/upgrade_comparison_config.py
odoo/addons/upgrade_analysis/models/upgrade_record.py
odoo/addons/upgrade_analysis/odoo_patch/__init__.py
odoo/addons/upgrade_analysis/odoo_patch/odoo_patch.py
odoo/addons/upgrade_analysis/odoo_patch/addons/__init__.py
odoo/addons/upgrade_analysis/odoo_patch/addons/mrp/__init__.py
odoo/addons/upgrade_analysis/odoo_patch/addons/point_of_sale/__init__.py
odoo/addons/upgrade_analysis/odoo_patch/addons/stock/__init__.py
odoo/addons/upgrade_analysis/odoo_patch/odoo/__init__.py
odoo/addons/upgrade_analysis/odoo_patch/odoo/models.py
odoo/addons/upgrade_analysis/odoo_patch/odoo/addons/__init__.py
odoo/addons/upgrade_analysis/odoo_patch/odoo/addons/base/__init__.py
odoo/addons/upgrade_analysis/odoo_patch/odoo/addons/base/models/__init__.py
odoo/addons/upgrade_analysis/odoo_patch/odoo/addons/base/models/ir_model.py
odoo/addons/upgrade_analysis/odoo_patch/odoo/modules/__init__.py
odoo/addons/upgrade_analysis/odoo_patch/odoo/modules/registry.py
odoo/addons/upgrade_analysis/odoo_patch/odoo/tools/__init__.py
odoo/addons/upgrade_analysis/odoo_patch/odoo/tools/convert.py
odoo/addons/upgrade_analysis/readme/CONTRIBUTORS.rst
odoo/addons/upgrade_analysis/readme/DESCRIPTION.rst
odoo/addons/upgrade_analysis/readme/ROADMAP.rst
odoo14_addon_upgrade_analysis-14.0.3.0.0.dist-info/METADATA
odoo14_addon_upgrade_analysis-14.0.3.0.0.dist-info/WHEEL
odoo14_addon_upgrade_analysis-14.0.3.0.0.dist-info/top_level.txt
odoo14_addon_upgrade_analysis-14.0.3.0.0.dist-info/RECORD
