Metadata-Version: 2.1
Name: odoo14-addon-upgrade-analysis
Version: 14.0.3.0.0
Summary: Performs a difference analysis between modules installed on two different Odoo instances
Home-page: https://github.com/OCA/server-tools
Author: Therp BV, Opener B.V., GRAP, Odoo Community Association (OCA)
Author-email: support@odoo-community.org
License: AGPL-3
Platform: UNKNOWN
Classifier: Programming Language :: Python
Classifier: Framework :: Odoo
Classifier: Framework :: Odoo :: 14.0
Classifier: License :: OSI Approved :: GNU Affero General Public License v3
Requires-Python: >=3.6
Requires-Dist: dataclasses
Requires-Dist: odoo (<14.1dev,>=14.0a)
Requires-Dist: odoorpc
Requires-Dist: openupgradelib
